uwotm8/__init__.py
uwotm8/__main__.py
uwotm8/convert.py
uwotm8-0.1.6.dist-info/LICENSE
uwotm8-0.1.6.dist-info/METADATA
uwotm8-0.1.6.dist-info/WHEEL
uwotm8-0.1.6.dist-info/entry_points.txt
uwotm8-0.1.6.dist-info/RECORD
