Metadata-Version: 2.3
Name: uwotm8
Version: 0.1.6
Summary: Converting American English to British English
License: MIT
Author: i.AI
Author-email: packages@cabinetoffice.gov.uk
Requires-Python: >=3.9
Classifier: License :: OSI Approved :: MIT License
Classifier: Programming Language :: Python :: 3
Classifier: Programming Language :: Python :: 3.9
Classifier: Programming Language :: Python :: 3.10
Classifier: Programming Language :: Python :: 3.11
Classifier: Programming Language :: Python :: 3.12
Classifier: Programming Language :: Python :: 3.13
Requires-Dist: breame (>=0.1.2,<0.2.0)
